pulpcore/cli/console/__init__.py
pulpcore/cli/console/populated_domain.py
pulpcore/cli/console/py.typed
pulpcore/cli/console/task.py
pulpcore/cli/console/vulnerability.py
pulp_cli_console-0.1.5.dev0.dist-info/METADATA
pulp_cli_console-0.1.5.dev0.dist-info/WHEEL
pulp_cli_console-0.1.5.dev0.dist-info/entry_points.txt
pulp_cli_console-0.1.5.dev0.dist-info/top_level.txt
pulp_cli_console-0.1.5.dev0.dist-info/RECORD
